iothello/__init__.py
iothello/backend_gui.py
iothello/font.otf
iothello/gui.py
iothello/models/0_ridge.sav
iothello/models/10_ridge.sav
iothello/models/11_ridge.sav
iothello/models/12_ridge.sav
iothello/models/13_ridge.sav
iothello/models/14_ridge.sav
iothello/models/15_ridge.sav
iothello/models/16_ridge.sav
iothello/models/17_ridge.sav
iothello/models/18_ridge.sav
iothello/models/19_ridge.sav
iothello/models/1_ridge.sav
iothello/models/20_ridge.sav
iothello/models/21_ridge.sav
iothello/models/22_ridge.sav
iothello/models/23_ridge.sav
iothello/models/24_ridge.sav
iothello/models/25_ridge.sav
iothello/models/26_ridge.sav
iothello/models/27_ridge.sav
iothello/models/28_ridge.sav
iothello/models/29_ridge.sav
iothello/models/2_ridge.sav
iothello/models/30_ridge.sav
iothello/models/31_ridge.sav
iothello/models/3_ridge.sav
iothello/models/4_ridge.sav
iothello/models/5_ridge.sav
iothello/models/6_ridge.sav
iothello/models/7_ridge.sav
iothello/models/8_ridge.sav
iothello/models/9_ridge.sav
iothello-1.1.7.dist-info/LICENCE.txt
iothello-1.1.7.dist-info/METADATA
iothello-1.1.7.dist-info/WHEEL
iothello-1.1.7.dist-info/top_level.txt
iothello-1.1.7.dist-info/RECORD
